db_plugins/__init__.py
db_plugins/cli/__init__.py
db_plugins/cli/manage.py
db_plugins/db/__init__.py
db_plugins/db/generic.py
db_plugins/db/mongo/__init__.py
db_plugins/db/mongo/_connection.py
db_plugins/db/mongo/helpers/__init__.py
db_plugins/db/mongo/helpers/update_probs.py
db_plugins/db/mongo/initialization.py
db_plugins/db/mongo/models.py
db_plugins/db/mongo/orm.py
db_plugins/db/sql/__init__.py
db_plugins/db/sql/_connection.py
db_plugins/db/sql/alembic.ini
db_plugins/db/sql/initialization.py
db_plugins/db/sql/migrations/README
db_plugins/db/sql/migrations/env.py
db_plugins/db/sql/migrations/script.py.mako
db_plugins/db/sql/models.py
db_plugins-27.4.0.dist-info/METADATA
db_plugins-27.4.0.dist-info/WHEEL
db_plugins-27.4.0.dist-info/entry_points.txt
db_plugins-27.4.0.dist-info/RECORD
