Metadata-Version: 2.3
Name: db-plugins
Version: 27.4.0
Summary: ALeRCE database plugins.
Requires-Python: >=3.7,<3.12
Classifier: Programming Language :: Python :: 3
Classifier: Programming Language :: Python :: 3.7
Classifier: Programming Language :: Python :: 3.8
Classifier: Programming Language :: Python :: 3.9
Classifier: Programming Language :: Python :: 3.10
Classifier: Programming Language :: Python :: 3.11
Requires-Dist: SQLAlchemy (==2.0.19)
Requires-Dist: alembic (==1.8.1)
Requires-Dist: click (==8.1.3)
Requires-Dist: pymongo (==4.4.1)
